assoc_scan/__init__.py
assoc_scan/assoc_scan.py
assoc_scan-0.0.4.dist-info/licenses/LICENSE
assoc_scan-0.0.4.dist-info/METADATA
assoc_scan-0.0.4.dist-info/WHEEL
assoc_scan-0.0.4.dist-info/top_level.txt
assoc_scan-0.0.4.dist-info/RECORD
