Metadata-Version: 2.4
Name: assoc-scan
Version: 0.0.4
Summary: Associative Scan
Author-email: Phil Wang <lucidrains@gmail.com>
License: MIT License
Project-URL: Homepage, https://pypi.org/project/assoc-scan/
Project-URL: Repository, https://github.com/lucidrains/assoc-scan
Keywords: artificial intelligence,deep learning
Classifier: Development Status :: 4 - Beta
Classifier: Intended Audience :: Developers
Classifier: Topic :: Scientific/Engineering :: Artificial Intelligence
Classifier: License :: OSI Approved :: MIT License
Classifier: Programming Language :: Python :: 3.8
Requires-Python: >=3.8
License-File: LICENSE
Requires-Dist: accelerated-scan>=0.3.0
Requires-Dist: einops>=0.8.0
Requires-Dist: torch>=2.0
Dynamic: license-file
